[
	{
		"slug": "cool-project",
		"name": "Cool project 1",
		"image": "placeholder.jpg",
		"url": "#",
		"date": "Jan 2014",
		"tags": ["Angular JS","API"]
	},
	{
		"name": "Cool project 2",
		"image": "placeholder.jpg",
		"url": "#",
		"date": "May 2014",
		"tags": ["Android","PHP"]
	},
	{
		"name": "Cool project 3",
		"image": "placeholder.jpg",
		"url": "#",
		"date": "June 2014",
		"tags": ["HTML","JQuery","PHP"]
	},
	{
		"name": "Cool project 4",
		"image": "placeholder.jpg",
		"date": "Oct 2016",
		"tags": ["Android","nodejs"]
	}

]